mistralvdb/__init__.py
mistralvdb/cli.py
mistralvdb/index.py
mistralvdb/storage.py
mistralvdb/vectordb.py
mistralvdb/api/__init__.py
mistralvdb/api/auth.py
mistralvdb/api/server.py
mistralvdb-0.1.0.dist-info/LICENSE
mistralvdb-0.1.0.dist-info/METADATA
mistralvdb-0.1.0.dist-info/WHEEL
mistralvdb-0.1.0.dist-info/entry_points.txt
mistralvdb-0.1.0.dist-info/top_level.txt
mistralvdb-0.1.0.dist-info/RECORD
